thysecser/__init__.py
thysecser-2026.0.dist-info/WHEEL
thysecser-2026.0.dist-info/METADATA
thysecser-2026.0.dist-info/RECORD
