Metadata-Version: 2.4
Name: thysecser
Version: 2026.0
Summary: Thycotic Secret Server API client
Author: William Jackson
Author-email: William Jackson <wjackson@informatica.com>
License-Expression: MIT
Classifier: Programming Language :: Python :: 3
Classifier: Operating System :: OS Independent
Requires-Dist: requests>=2.32.3
Requires-Python: >=3.10
Project-URL: Homepage, https://github.com/informatica-na-presales-ops/thycotic-secret-server-api
Project-URL: Issues, https://github.com/informatica-na-presales-ops/thycotic-secret-server-api/issues
